sdf_sampler/__init__.py
sdf_sampler/__main__.py
sdf_sampler/analyzer.py
sdf_sampler/cli.py
sdf_sampler/config.py
sdf_sampler/io.py
sdf_sampler/sampler.py
sdf_sampler/algorithms/__init__.py
sdf_sampler/algorithms/flood_fill.py
sdf_sampler/algorithms/normal_idw.py
sdf_sampler/algorithms/normal_offset.py
sdf_sampler/algorithms/pocket.py
sdf_sampler/algorithms/voxel_grid.py
sdf_sampler/algorithms/voxel_regions.py
sdf_sampler/models/__init__.py
sdf_sampler/models/analysis.py
sdf_sampler/models/constraints.py
sdf_sampler/models/samples.py
sdf_sampler/sampling/__init__.py
sdf_sampler/sampling/box.py
sdf_sampler/sampling/brush.py
sdf_sampler/sampling/ray_carve.py
sdf_sampler/sampling/sphere.py
sdf_sampler-0.5.0.dist-info/METADATA
sdf_sampler-0.5.0.dist-info/WHEEL
sdf_sampler-0.5.0.dist-info/entry_points.txt
sdf_sampler-0.5.0.dist-info/licenses/LICENSE
sdf_sampler-0.5.0.dist-info/RECORD
