Metadata-Version: 2.4
Name: sdf-sampler
Version: 0.5.0
Summary: Auto-analysis and sampling of point clouds for SDF (Signed Distance Field) training data generation
Project-URL: Repository, https://github.com/Chiark-Collective/sdf-sampler
Author-email: Liam <liam@example.com>
License: MIT
License-File: LICENSE
Keywords: machine-learning,point-cloud,sampling,sdf,signed-distance-field
Classifier: Development Status :: 4 - Beta
Classifier: Intended Audience :: Developers
Classifier: Intended Audience :: Science/Research
Classifier: License :: OSI Approved :: MIT License
Classifier: Programming Language :: Python :: 3
Classifier: Programming Language :: Python :: 3.11
Classifier: Programming Language :: Python :: 3.12
Classifier: Topic :: Scientific/Engineering
Classifier: Topic :: Scientific/Engineering :: Artificial Intelligence
Requires-Python: >=3.11
Requires-Dist: alphashape>=1.3.1
Requires-Dist: numpy>=1.26.0
Requires-Dist: pandas>=2.1.0
Requires-Dist: pyarrow>=14.0.0
Requires-Dist: pydantic>=2.5.0
Requires-Dist: scipy>=1.11.0
Provides-Extra: all
Requires-Dist: laspy[laszip]>=2.5.0; extra == 'all'
Requires-Dist: mypy>=1.8.0; extra == 'all'
Requires-Dist: pytest-asyncio>=0.23.0; extra == 'all'
Requires-Dist: pytest-cov>=4.0.0; extra == 'all'
Requires-Dist: pytest>=8.0.0; extra == 'all'
Requires-Dist: ruff>=0.5.0; extra == 'all'
Requires-Dist: trimesh>=4.0.0; extra == 'all'
Provides-Extra: dev
Requires-Dist: mypy>=1.8.0; extra == 'dev'
Requires-Dist: pytest-asyncio>=0.23.0; extra == 'dev'
Requires-Dist: pytest-cov>=4.0.0; extra == 'dev'
Requires-Dist: pytest>=8.0.0; extra == 'dev'
Requires-Dist: ruff>=0.5.0; extra == 'dev'
Provides-Extra: io
Requires-Dist: laspy[laszip]>=2.5.0; extra == 'io'
Requires-Dist: trimesh>=4.0.0; extra == 'io'
